quri_parts/itensor/NOTICE
quri_parts/itensor/__init__.py
quri_parts/itensor/circuit/__init__.py
quri_parts/itensor/estimator.py
quri_parts/itensor/library.jl
quri_parts/itensor/load_itensor.py
quri_parts/itensor/operator/__init__.py
quri_parts/itensor/py.typed
quri_parts/itensor/sampler.py
quri_parts_itensor-17.0.0.dist-info/METADATA
quri_parts_itensor-17.0.0.dist-info/WHEEL
quri_parts_itensor-17.0.0.dist-info/RECORD
